rentcache/__init__.py
rentcache/cache.py
rentcache/cli.py
rentcache/config.py
rentcache/models.py
rentcache/server.py
rentcache-0.1.1.dist-info/METADATA
rentcache-0.1.1.dist-info/WHEEL
rentcache-0.1.1.dist-info/entry_points.txt
rentcache-0.1.1.dist-info/licenses/LICENSE
rentcache-0.1.1.dist-info/RECORD
