Metadata-Version: 2.4
Name: rentcache
Version: 0.1.1
Summary: Intelligent caching proxy for Rentcast API with cost management and rate limiting
Project-URL: Homepage, https://git.supported.systems/MCP/rentcache
Project-URL: Repository, https://git.supported.systems/MCP/rentcache.git
Project-URL: Documentation, https://git.supported.systems/MCP/rentcache#readme
Project-URL: Bug Tracker, https://git.supported.systems/MCP/rentcache/issues
Author-email: Ryan Malloy <ryan@supported.systems>
License: MIT
License-File: LICENSE
Keywords: api,cache,property-data,proxy,rate-limiting,real-estate,rentcast
Classifier: Development Status :: 4 - Beta
Classifier: Intended Audience :: Developers
Classifier: License :: OSI Approved :: MIT License
Classifier: Programming Language :: Python :: 3
Classifier: Programming Language :: Python :: 3.10
Classifier: Programming Language :: Python :: 3.11
Classifier: Programming Language :: Python :: 3.12
Classifier: Programming Language :: Python :: 3.13
Classifier: Topic :: Database :: Front-Ends
Classifier: Topic :: Internet :: Proxy Servers
Classifier: Topic :: Software Development :: Libraries :: Python Modules
Requires-Python: >=3.10
Requires-Dist: aiosqlite>=0.20.0
Requires-Dist: click>=8.1.0
Requires-Dist: fastapi>=0.115.0
Requires-Dist: httpx>=0.27.0
Requires-Dist: pydantic-settings>=2.0.0
Requires-Dist: pydantic>=2.10.0
Requires-Dist: python-dotenv>=1.0.0
Requires-Dist: python-multipart>=0.0.12
Requires-Dist: redis>=5.0.0
Requires-Dist: rich>=13.0.0
Requires-Dist: slowapi>=0.1.9
Requires-Dist: sqlalchemy>=2.0.0
Requires-Dist: structlog>=24.0.0
Requires-Dist: tenacity>=9.0.0
Requires-Dist: uvicorn[standard]>=0.32.0
